funcnodes_core/__init__.py
funcnodes_core/_logging.py
funcnodes_core/_setup.py
funcnodes_core/config.py
funcnodes_core/data.py
funcnodes_core/datapath.py
funcnodes_core/eventmanager.py
funcnodes_core/exceptions.py
funcnodes_core/graph.py
funcnodes_core/grouping_logic.py
funcnodes_core/io.py
funcnodes_core/node.py
funcnodes_core/nodemaker.py
funcnodes_core/nodespace.py
funcnodes_core/testing.py
funcnodes_core/triggerstack.py
funcnodes_core/decorator/__init__.py
funcnodes_core/lib/__init__.py
funcnodes_core/lib/lib.py
funcnodes_core/lib/libfinder.py
funcnodes_core/lib/libparser.py
funcnodes_core/utils/__init__.py
funcnodes_core/utils/cache.py
funcnodes_core/utils/data.py
funcnodes_core/utils/deprecations.py
funcnodes_core/utils/files.py
funcnodes_core/utils/functions.py
funcnodes_core/utils/modules.py
funcnodes_core/utils/nodetqdm.py
funcnodes_core/utils/nodeutils.py
funcnodes_core/utils/plugins.py
funcnodes_core/utils/plugins_types.py
funcnodes_core/utils/saving.py
funcnodes_core/utils/serialization.py
funcnodes_core/utils/special_types.py
funcnodes_core/utils/wrapper.py
funcnodes_core-2.2.0.dist-info/METADATA
funcnodes_core-2.2.0.dist-info/WHEEL
funcnodes_core-2.2.0.dist-info/licenses/LICENSE
funcnodes_core-2.2.0.dist-info/RECORD
