Metadata-Version: 2.4
Name: funcnodes-core
Version: 2.2.0
Summary: core package for funcnodes
Project-URL: homepage, https://github.com/Linkdlab/funcnodes_core
Project-URL: source, https://github.com/Linkdlab/funcnodes_core
Project-URL: tracker, https://github.com/Linkdlab/funcnodes_core/issues
Project-URL: download, https://pypi.org/project/funcnodes-core/#files
Author-email: Julian Kimmig <julian.kimmig@linkdlab.de>
License: AGPL-3.0
License-File: LICENSE
Classifier: Development Status :: 4 - Beta
Classifier: Intended Audience :: Developers
Classifier: Intended Audience :: Education
Classifier: Intended Audience :: Science/Research
Classifier: License :: OSI Approved :: GNU Affero General Public License v3 or later (AGPLv3+)
Requires-Python: >=3.11
Requires-Dist: dill
Requires-Dist: exposedfunctionality>=1.0.2
Requires-Dist: pytest-funcnodes>=1.0.0
Requires-Dist: python-dotenv
Requires-Dist: setuptools
Requires-Dist: tqdm
Provides-Extra: dev
Requires-Dist: coverage>=7.6.12; extra == 'dev'
Requires-Dist: funcnodes-basic>=0.2.1; extra == 'dev'
Requires-Dist: funcnodes>=1.0.0; extra == 'dev'
Requires-Dist: pre-commit>=4.1.0; extra == 'dev'
Requires-Dist: pytest-asyncio; extra == 'dev'
Requires-Dist: pytest-asyncio>=0.25.3; extra == 'dev'
Requires-Dist: pytest-cov; extra == 'dev'
Requires-Dist: pytest-funcnodes>=0.1.0; extra == 'dev'
Requires-Dist: pytest-timeout; extra == 'dev'
Requires-Dist: pytest-xdist>=3.6.1; extra == 'dev'
Requires-Dist: pytest>=8.3.4; extra == 'dev'
Requires-Dist: vulture>=2.14; extra == 'dev'
Requires-Dist: yappi>=1.6.10; extra == 'dev'
